MANIFEST.in
README.rst
ez_setup.py
setup.py
redlib/__init__.py
redlib/api.py
redlib/version.py
redlib.egg-info/PKG-INFO
redlib.egg-info/SOURCES.txt
redlib.egg-info/dependency_links.txt
redlib.egg-info/requires.txt
redlib.egg-info/top_level.txt
redlib/colors/__init__.py
redlib/colors/clist.py
redlib/colors/colortrans.py
redlib/http/__init__.py
redlib/http/cache.py
redlib/http/http_request.py
redlib/image/__init__.py
redlib/image/imageinfo.py
redlib/misc/__init__.py
redlib/misc/docstring.py
redlib/misc/func.py
redlib/misc/logger.py
redlib/misc/makeapi.py
redlib/misc/retry.py
redlib/misc/retry2.py
redlib/misc/singleton.py
redlib/misc/textfile.py
redlib/net/__init__.py
redlib/net/all.py
redlib/net/cdns.py
redlib/net/tlds.py
redlib/net/update_cdns.py
redlib/net/update_tlds.py
redlib/net/urls.py
redlib/prnt/__init__.py
redlib/prnt/column_printer.py
redlib/prnt/func.py
redlib/py23/__init__.py
redlib/py23/lang23.py
redlib/py23/pickle23.py
redlib/system/__init__.py
redlib/system/common.py
redlib/system/crondbus.py
redlib/system/scheduler.py
redlib/system/sys_command.py
redlib/system/terminalsize.py
redlib/testlib/__init__.py
redlib/testlib/testorder.py
redlib/testlib/testrunner.py
redlib/web/__init__.py
redlib/web/htmlparser.py
redlib/web/htmlparser_debugger.py